ntlm3/HTTPNtlmAuthHandler.py
ntlm3/U32.py
ntlm3/__init__.py
ntlm3/compat.py
ntlm3/des.py
ntlm3/des_c.py
ntlm3/des_data.py
ntlm3/ntlm.py
python_ntlm6-1.0.5.dist-info/LICENSE.md
python_ntlm6-1.0.5.dist-info/METADATA
python_ntlm6-1.0.5.dist-info/WHEEL
python_ntlm6-1.0.5.dist-info/top_level.txt
python_ntlm6-1.0.5.dist-info/RECORD
